{"components_button.md":"8b905424","components_config-provider.md":"934fab2f","components_date-picker.md":"b896da11","components_dialog.md":"14af077a","components_form.md":"d5675c3c","components_input.md":"d31f49ba","components_motion.md":"a8e6e573","components_search.md":"332411fb","components_select.md":"6851874d","components_status.md":"e0545ffa","components_table.md":"d8e972f7","components_upload.md":"54b18108","guide_changelog.md":"2491f800","guide_install.md":"8f71d7ed","guide_quick-start.md":"921a5a28","index.md":"7cacba36"}
