{"components_button.md":"cdc10b68","components_config-provider.md":"f6a8b5d2","components_date-picker.md":"57647d76","components_dialog.md":"afffc358","components_form.md":"1d88abf1","components_input.md":"1bcd55c2","components_motion.md":"de244383","components_search.md":"b1f9eff6","components_select.md":"0e413ea5","components_status.md":"11d0b2d7","components_table.md":"becf1ec1","components_upload.md":"ac965457","guide_changelog.md":"46c4433c","guide_install.md":"b8818542","guide_quick-start.md":"d4616e39","index.md":"127a692b"}
